tdameritrade/__init__.py
tdameritrade/client.py
tdameritrade/enums.py
tdameritrade/exceptions.py
tdameritrade/order.py
tdameritrade/session.py
tdameritrade/streaming.py
tdameritrade/urls.py
tdameritrade/auth/__init__.py
tdameritrade/auth/__main__.py
tdameritrade/orders/__init__.py
tdameritrade/orders/constants.py
tdameritrade/orders/leg_builder.py
tdameritrade/orders/order_builder.py
tdameritrade/orders/models/__init__.py
tdameritrade/orders/models/activities.py
tdameritrade/orders/models/base.py
tdameritrade/orders/models/instruments.py
tdameritrade/orders/models/json_encoder.py
tdameritrade/orders/models/leg.py
tdameritrade/orders/models/orders.py
tdameritrade-0.2.1.dist-info/LICENSE
tdameritrade-0.2.1.dist-info/METADATA
tdameritrade-0.2.1.dist-info/WHEEL
tdameritrade-0.2.1.dist-info/entry_points.txt
tdameritrade-0.2.1.dist-info/top_level.txt
tdameritrade-0.2.1.dist-info/RECORD
