Metadata-Version: 2.1
Name: tdameritrade
Version: 0.2.1
Summary: APIs for TD Ameritrade
Home-page: https://github.com/timkpaine/tdameritrade
Author: Tim Paine
Author-email: t.paine154@gmail.com
License: Apache 2.0
Keywords: finance data
Classifier: Development Status :: 3 - Alpha
Classifier: Programming Language :: Python :: 3
Classifier: Programming Language :: Python :: 3.6
Classifier: Programming Language :: Python :: 3.7
Classifier: Programming Language :: Python :: 3.8
License-File: LICENSE
Requires-Dist: pandas (>=0.22.0)
Requires-Dist: requests (>=2.23.0)
Provides-Extra: auth
Requires-Dist: selenium (>=3.141.0) ; extra == 'auth'
Provides-Extra: dev
Requires-Dist: black (>=23) ; extra == 'dev'
Requires-Dist: bump2version (>=1.0.0) ; extra == 'dev'
Requires-Dist: flake8 (>=3.7.8) ; extra == 'dev'
Requires-Dist: flake8-black (>=0.2.1) ; extra == 'dev'
Requires-Dist: mock ; extra == 'dev'
Requires-Dist: pytest (>=4.3.0) ; extra == 'dev'
Requires-Dist: pytest-cov (>=2.6.1) ; extra == 'dev'
Requires-Dist: Sphinx (>=1.8.4) ; extra == 'dev'
Requires-Dist: sphinx-markdown-builder (>=0.5.2) ; extra == 'dev'
Requires-Dist: pandas (>=0.22.0) ; extra == 'dev'
Requires-Dist: requests (>=2.23.0) ; extra == 'dev'
Requires-Dist: selenium (>=3.141.0) ; extra == 'dev'
